leitner_box/__init__.py
leitner_box/leitner_box.py
leitner_box-0.3.0.dist-info/LICENSE
leitner_box-0.3.0.dist-info/METADATA
leitner_box-0.3.0.dist-info/WHEEL
leitner_box-0.3.0.dist-info/top_level.txt
leitner_box-0.3.0.dist-info/RECORD
