Metadata-Version: 2.1
Name: leitner_box
Version: 0.3.0
Summary: Leitner system spaced repetition
Author-email: Joshua Hamilton <hamiltonjoshuadavid@gmail.com>
License: MIT License
Project-URL: homepage, https://github.com/open-spaced-repetition/leitner-box
Keywords: leitner,spaced-repetition,flashcard
Classifier: Programming Language :: Python :: 3
Classifier: License :: OSI Approved :: MIT License
Classifier: Operating System :: OS Independent
Requires-Python: >=3.10
License-File: LICENSE
